tbselenium_macos/__init__.py
tbselenium_macos/common.py
tbselenium_macos/exceptions.py
tbselenium_macos/tbdriver.py
tbselenium_macos/utils.py
tbselenium_macos/test/__init__.py
tbselenium_macos/test/conftest.py
tbselenium_macos/test/fixtures.py
tbselenium_macos/test/test_addons.py
tbselenium_macos/test/test_browser.py
tbselenium_macos/test/test_disable_features.py
tbselenium_macos/test/test_exceptions.py
tbselenium_macos/test/test_security_level.py
tbselenium_macos/test/test_stem.py
tbselenium_macos/test/test_tbdriver.py
tbselenium_macos/test/test_utils.py
tbselenium_macos/test/test_data/img_test.html
tbselenium_macos/test/test_data/js_test.html
tbselenium_macos-1.0.0.dist-info/licenses/LICENSE
tbselenium_macos-1.0.0.dist-info/METADATA
tbselenium_macos-1.0.0.dist-info/WHEEL
tbselenium_macos-1.0.0.dist-info/top_level.txt
tbselenium_macos-1.0.0.dist-info/RECORD
