Metadata-Version: 2.4
Name: tbselenium-macos
Version: 1.0.0
Summary: Tor Browser automation with Selenium for macOS
Author: tbselenium-macos contributors
License: MIT
Project-URL: Homepage, https://github.com/maximilianromer/tbselenium-macos
Project-URL: Bug Reports, https://github.com/maximilianromer/tbselenium-macos/issues
Project-URL: Source, https://github.com/maximilianromer/tbselenium-macos
Keywords: tor,selenium,tor browser,macos,browser automation,privacy
Classifier: Development Status :: 4 - Beta
Classifier: Environment :: MacOS X
Classifier: Intended Audience :: Developers
Classifier: License :: OSI Approved :: MIT License
Classifier: Operating System :: MacOS :: MacOS X
Classifier: Programming Language :: Python :: 3
Classifier: Programming Language :: Python :: 3.8
Classifier: Programming Language :: Python :: 3.9
Classifier: Programming Language :: Python :: 3.10
Classifier: Programming Language :: Python :: 3.11
Classifier: Programming Language :: Python :: 3.12
Classifier: Topic :: Internet :: WWW/HTTP :: Browsers
Classifier: Topic :: Software Development :: Testing
Classifier: Topic :: Security
Requires-Python: >=3.8
License-File: LICENSE
Requires-Dist: selenium>=4.0.0
Provides-Extra: dev
Requires-Dist: pytest>=7.0.0; extra == "dev"
Requires-Dist: pytest-cov>=4.0.0; extra == "dev"
Requires-Dist: stem>=1.8.0; extra == "dev"
Requires-Dist: black; extra == "dev"
Requires-Dist: isort; extra == "dev"
Requires-Dist: mypy; extra == "dev"
Provides-Extra: stem
Requires-Dist: stem>=1.8.0; extra == "stem"
Dynamic: license-file
